{
  "users": [
    {
      "id": 1,
      "userName": "Matt",
      "password": "1234"
    },
    {
      "userName": "mattScott32",
      "password": "1111",
      "id": 2
    },
    {
      "userName": "Jisie",
      "password": "1212",
      "id": 3
    },
    {
      "userName": "Corri",
      "password": "2222",
      "id": 4
    },
    {
      "userName": "Chase",
      "password": "3333",
      "id": 5
    },
    {
      "userName": "Erin",
      "password": "4444",
      "id": 6
    },
    {
      "userName": "Bito",
      "password": "5555",
      "id": 7
    },
    {
      "userName": "Shawna",
      "password": "6666",
      "id": 8
    },
    {
      "userName": "manila",
      "password": "8888",
      "id": 9
    },
    {
      "userName": "Adam",
      "password": "9999",
      "id": 10
    },
    {
      "userName": "Bradley Pitts",
      "password": "0000",
      "id": 11
    },
    {
      "userName": "Jimmy",
      "password": "3232",
      "id": 12
    },
    {
      "userName": "harry",
      "password": "1313",
      "id": 13
    },
    {
      "userName": "Matthew",
      "password": "2323",
      "id": 14
    },
    {
      "userName": "ryan",
      "password": "6464",
      "id": 15
    },
    {
      "userName": "julian",
      "password": "4567",
      "id": 16
    },
    {
      "userName": "Rose",
      "password": "420",
      "id": 17
    },
    {
      "userName": "Dad",
      "password": "6464",
      "id": 18
    },
    {
      "userName": "chase",
      "password": "1111",
      "id": 19
    },
    {
      "userName": "Ryan",
      "password": "5656",
      "id": 20
    },
    {
      "userName": "Kristen",
      "password": "9999",
      "id": 21
    },
    {
      "userName": "Steve",
      "password": "5555",
      "id": 22
    },
    {
      "userName": "Mike",
      "password": "1111",
      "id": 23
    },
    {
      "userName": "bob",
      "password": "1234",
      "id": 24
    },
    {
      "userName": "chase fizzite",
      "password": "1111",
      "id": 25
    },
    {
      "userName": "coco",
      "password": "1111",
      "id": 26
    },
    {
      "userName": "Jimmy",
      "password": "1111",
      "id": 27
    },
    {
      "userName": "Sam",
      "password": "5555",
      "id": 28
    },
    {
      "userName": "Jimmy Joe Joe",
      "password": "6565",
      "id": 29
    },
    {
      "userName": "Matt2",
      "password": "4321",
      "id": 30
    },
    {
      "userName": "Mitch",
      "password": "4321",
      "id": 31
    }
  ],
  "shoes": [
    {
      "userId": 5,
      "brand": "Adidas",
      "model": "Fudge",
      "size": "4 1/2",
      "dateOfPurchase": "2019-12-15",
      "mileage": "20",
      "injuries": "blister-15",
      "condition": "Heel Tore- 20",
      "trailRoadBoth": "Road",
      "weight": "Light",
      "racesUsed": "none",
      "current": false,
      "id": 2
    },
    {
      "userId": 20,
      "brand": "Flips",
      "model": "Giants",
      "size": "5",
      "dateOfPurchase": "2019-12-17",
      "mileage": "2",
      "injuries": "none",
      "condition": "fair",
      "trailRoadBoth": "Trail",
      "weight": "Medium",
      "racesUsed": "none",
      "current": false,
      "id": 8
    },
    {
      "userId": 19,
      "brand": "British",
      "model": "x27",
      "size": "5",
      "dateOfPurchase": "2019-12-17",
      "mileage": "4",
      "injuries": "none",
      "condition": "bad",
      "trailRoadBoth": "Trail",
      "weight": "Medium",
      "racesUsed": "none",
      "current": false,
      "id": 9
    },
    {
      "id": 11,
      "userId": 23,
      "brand": "Reebok",
      "model": "Highs",
      "size": "10",
      "dateOfPurchase": "2019-12-18",
      "mileage": "2",
      "injuries": "none",
      "trailRoadBoth": "Road",
      "weight": "Light",
      "racesUsed": "none",
      "current": true
    },
    {
      "id": 12,
      "userId": 25,
      "brand": "british knights",
      "model": "x46",
      "size": "10",
      "dateOfPurchase": "2019-12-11",
      "mileage": "4",
      "injuries": "blisters",
      "condition": "pain at 11th mile",
      "trailRoadBoth": "Trail",
      "weight": "Heavy",
      "racesUsed": "1",
      "current": true
    },
    {
      "userId": 25,
      "brand": "nike",
      "model": "jordan",
      "size": "11",
      "dateOfPurchase": "2019-12-26",
      "mileage": "111",
      "injuries": "none",
      "condition": "perfect",
      "trailRoadBoth": "Trail",
      "weight": "Heavy",
      "racesUsed": "none",
      "current": true,
      "id": 13
    },
    {
      "id": 14,
      "userId": 27,
      "brand": "Nike",
      "model": "Ghosts",
      "size": "9",
      "dateOfPurchase": "2019-12-01",
      "mileage": "20",
      "injuries": "shin splints",
      "condition": "heel started to come off after 10",
      "trailRoadBoth": "Road",
      "weight": "Light",
      "racesUsed": "none",
      "current": false
    },
    {
      "id": 15,
      "userId": 27,
      "brand": "Puma",
      "model": "Fudges",
      "size": "10",
      "dateOfPurchase": "2019-11-01",
      "mileage": "50",
      "injuries": "blister on left big toe",
      "condition": "started to fall apart after 25 miles",
      "trailRoadBoth": "Trail",
      "weight": "Medium",
      "racesUsed": "none",
      "current": true
    },
    {
      "id": 17,
      "userId": 1,
      "brand": "reebok",
      "model": "shoe",
      "size": "9",
      "dateOfPurchase": "2019-12-20",
      "mileage": "5",
      "injuries": "none",
      "condition": "fair",
      "trailRoadBoth": "road",
      "weight": "medium",
      "racesUsed": "none",
      "current": true
    },
    {
      "userId": 4,
      "brand": "nike",
      "model": "shoe",
      "size": "09",
      "dateOfPurchase": "2019-12-17",
      "mileage": "5",
      "injuries": "none",
      "condition": "fair",
      "trailRoadBoth": "both",
      "weight": "light",
      "racesUsed": "none",
      "current": true,
      "id": 18
    },
    {
      "id": 19,
      "userId": 1,
      "brand": "Nike",
      "model": "Shoes",
      "size": "9",
      "dateOfPurchase": "2019-12-31",
      "mileage": "5",
      "injuries": "blister",
      "condition": "toe blew out-10 miles",
      "trailRoadBoth": "trail",
      "weight": "light",
      "racesUsed": "Murray 5k",
      "current": false
    },
    {
      "userId": 1,
      "brand": "Puma",
      "model": "Shoes",
      "size": "10",
      "dateOfPurchase": "2019-12-23",
      "mileage": "4",
      "injuries": "none",
      "condition": "toe blown out-20",
      "trailRoadBoth": "road",
      "weight": "medium",
      "racesUsed": "benton race",
      "current": false,
      "id": 20
    },
    {
      "userId": 1,
      "brand": "Brooks",
      "model": "shoe",
      "size": "9",
      "dateOfPurchase": "2020-01-02",
      "mileage": "4",
      "injuries": "blister",
      "condition": "good",
      "trailRoadBoth": "trail",
      "weight": "light",
      "racesUsed": "none",
      "current": false,
      "id": 21
    },
    {
      "userId": 1,
      "brand": "Brooks 2",
      "model": "shoe",
      "size": "11",
      "dateOfPurchase": "2020-01-08",
      "mileage": "5",
      "injuries": "none",
      "condition": "sole wore out after 30 miles",
      "trailRoadBoth": " both",
      "weight": "light",
      "racesUsed": "none",
      "current": false,
      "id": 22
    }
  ],
  "races": [
    {
      "userId": 5,
      "raceName": "Color Run for Manila Awareness",
      "raceLocation": "Nashville",
      "raceDate": "2019-12-18",
      "raceTime": "22:00",
      "distance": "3.1",
      "placement": "1",
      "shoeId": 2,
      "id": 3
    },
    {
      "userId": 23,
      "raceName": "Bunion Fun Run",
      "raceLocation": "Nashville",
      "raceDate": "2019-12-18",
      "raceTime": "21:00",
      "distance": "3.1",
      "placement": "2",
      "shoeId": 11,
      "id": 4
    },
    {
      "userId": 25,
      "raceName": "west coast",
      "raceLocation": "nyc",
      "raceDate": "2019-12-11",
      "raceTime": "10:00Am",
      "distance": "26 miles",
      "placement": "3",
      "shoeId": 13,
      "id": 5
    },
    {
      "id": 6,
      "userId": 27,
      "raceName": "Run for Bat Rabies Awareness",
      "raceLocation": "Nashville",
      "raceDate": "2019-12-18",
      "raceTime": "22:43",
      "distance": "3.1",
      "placement": "3",
      "shoeId": "15"
    },
    {
      "id": 9,
      "userId": 4,
      "raceName": "hlll",
      "raceLocation": "ehjofiw",
      "raceDate": "2019-12-20",
      "raceTime": "2443",
      "distance": "122",
      "placement": "1",
      "shoeId": 18
    },
    {
      "id": 12,
      "userId": 1,
      "raceName": "Nashville Race",
      "raceLocation": "Nashville",
      "raceDate": "2019-12-24",
      "raceTime": "24:00",
      "distance": "3.1",
      "placement": "4",
      "shoeId": "19"
    },
    {
      "id": 13,
      "userId": 1,
      "raceName": "Benton Race",
      "raceLocation": "Benton",
      "raceDate": "2020-01-01",
      "raceTime": "23:00",
      "distance": "3.1",
      "placement": "1",
      "shoeId": 19
    },
    {
      "id": 14,
      "userId": 1,
      "raceName": "Murray Race",
      "raceLocation": "Murray",
      "raceDate": "2020-01-01",
      "raceTime": "22:00",
      "distance": "3.1",
      "placement": "2",
      "shoeId": "19"
    },
    {
      "id": 15,
      "userId": 1,
      "raceName": "Chicago Race",
      "raceLocation": "Chicago",
      "raceDate": "2020-01-02",
      "raceTime": "22:00",
      "distance": "3.1",
      "placement": "4",
      "shoeId": "21"
    },
    {
      "id": 16,
      "userId": 1,
      "raceName": "St. Louis Race",
      "raceLocation": "St. Louis",
      "raceDate": "2020-01-01",
      "raceTime": "24:30",
      "distance": "3.1",
      "placement": "8",
      "shoeId": "21"
    }
  ]
}